core/__init__.py
core/analyzer.py
core/chunking.py
document_analysis_framework-1.1.0.dist-info/licenses/LICENSE
handlers/HANDLER_IMPLEMENTATION_CHECKLIST.md
handlers/__init__.py
handlers/api_definition_handlers.py
handlers/api_documentation_handlers.py
handlers/automation_handlers.py
handlers/code_handlers.py
handlers/code_handlers_extended.py
handlers/config_handlers.py
handlers/config_handlers_extended.py
handlers/container_orchestration_handlers.py
handlers/kubernetes_handlers.py
handlers/notebook_ci_handlers.py
handlers/python_package_handlers.py
handlers/scientific_code_handlers.py
handlers/text_handlers.py
handlers/text_handlers_extended.py
handlers/web_component_handlers.py
handlers/web_style_handlers.py
utils/__init__.py
utils/file_utils.py
document_analysis_framework-1.1.0.dist-info/METADATA
document_analysis_framework-1.1.0.dist-info/WHEEL
document_analysis_framework-1.1.0.dist-info/top_level.txt
document_analysis_framework-1.1.0.dist-info/RECORD
